setup.py
wcolors/__init__.py
wcolors/wcolors.py
wcolors.egg-info/PKG-INFO
wcolors.egg-info/SOURCES.txt
wcolors.egg-info/dependency_links.txt
wcolors.egg-info/requires.txt
wcolors.egg-info/top_level.txt