Metadata-Version: 1.0
Name: wcolors
Version: 1.0
Summary: A python module for use colors in Windows 
Home-page: https://github.com/SarbazVatan/wcolors
Author: Soldier_of_iran
Author-email: soldier.of.iran.dev@gmail.com
License: UNKNOWN
Platform: UNKNOWN
